processss/__init__.py
processss/processing/__init__.py
processss/processing/plot.py
processss-0.0.1.dist-info/METADATA
processss-0.0.1.dist-info/WHEEL
processss-0.0.1.dist-info/top_level.txt
processss-0.0.1.dist-info/RECORD
