Metadata-Version: 2.4
Name: processss
Version: 0.0.1
Summary: Ferramentas para plotar imagem
Author: Daniel Sans Reppso da Silva
Author-email: danielsansrj@gmail.com
Requires-Python: >=3.8
Requires-Dist: matplotlib
Dynamic: author
Dynamic: author-email
Dynamic: description
Dynamic: description-content-type
Dynamic: requires-dist
Dynamic: requires-python
Dynamic: summary
